RoverRetriever/__init__.py
RoverRetriever/retriever.py
RoverRetriever/rover_retriever.py
RoverRetriever-0.1.5.dist-info/LICENSE
RoverRetriever-0.1.5.dist-info/METADATA
RoverRetriever-0.1.5.dist-info/WHEEL
RoverRetriever-0.1.5.dist-info/top_level.txt
RoverRetriever-0.1.5.dist-info/RECORD
