Metadata-Version: 2.1
Name: RoverRetriever
Version: 0.1.5
Summary: RoverRetriever is a lightweight Python wrapper written to facilitate interaction with the Dog CEO API.
Home-page: https://github.com/tyler-tee/RoverRetriever
Author: Tyler Talaga
Author-email: ttalaga@wgu.edu
License: MIT
Platform: UNKNOWN
Classifier: Programming Language :: Python :: 3.6
Classifier: Programming Language :: Python :: 3.7
Classifier: Programming Language :: Python :: 3.8
Classifier: Programming Language :: Python :: 3.9
Classifier: Programming Language :: Python :: 3.10
Classifier: Programming Language :: Python :: 3.11
Requires-Dist: requests >=2.25.1
